OpenAIChatHelper/ChatCompletionEndPoint.py
OpenAIChatHelper/Config.py
OpenAIChatHelper/EndPoint.py
OpenAIChatHelper/__init__.py
OpenAIChatHelper/message/Contents.py
OpenAIChatHelper/message/Message.py
OpenAIChatHelper/message/MessageList.py
OpenAIChatHelper/message/SubstitutionDict.py
OpenAIChatHelper/message/ToolCall.py
OpenAIChatHelper/message/__init__.py
OpenAIChatHelper/utils/Logging.py
OpenAIChatHelper/utils/StringOperations.py
OpenAIChatHelper/utils/__init__.py
openaichathelper-0.1.1.2.dist-info/METADATA
openaichathelper-0.1.1.2.dist-info/WHEEL
openaichathelper-0.1.1.2.dist-info/licenses/LICENSE
openaichathelper-0.1.1.2.dist-info/RECORD
