Metadata-Version: 2.4
Name: OpenAIChatHelper
Version: 0.1.1.2
Summary: A helper package for OpenAI API
Project-URL: Homepage, https://github.com/hyn0027/OpenAIChatHelper
Project-URL: Issues, https://github.com/hyn0027/OpenAIChatHelper/issues
Author-email: Yining Hong <yhong3@andrew.cmu.edu>
License: MIT
License-File: LICENSE
Classifier: License :: OSI Approved :: MIT License
Classifier: Operating System :: OS Independent
Classifier: Programming Language :: Python :: 3
Requires-Python: >=3.8
Requires-Dist: markdown-it-py>=3.0.0
Requires-Dist: mdformat>=0.7.0
Requires-Dist: openai>=1.0.0
